{"cameraMode":{"drawMode":0,"name":"Shaded","section":"Shading Mode"},"sceneLighting":false,"audioPlay":false,"sceneViewState":{"showFog":true,"showMaterialUpdate":false,"showSkybox":false,"showFlares":true,"showImageEffects":true,"showParticleSystems":true},"in2DMode":false,"pivot":{"x":-0.12690308690071107,"y":1.0787626504898072,"z":1.1086835861206055},"rotation":{"x":-0.11353884637355805,"y":-0.8635690808296204,"z":0.22428825497627259,"w":-0.43713295459747317},"size":2.767138719558716,"orthographic":false}